keogram/__init__.py
keogram/keogram.py
keogram-1.0.0.dist-info/LICENSE.md
keogram-1.0.0.dist-info/METADATA
keogram-1.0.0.dist-info/WHEEL
keogram-1.0.0.dist-info/top_level.txt
keogram-1.0.0.dist-info/RECORD
