Metadata-Version: 2.1
Name: keogram
Version: 1.0.0
Summary: Generate a Keogram from a directory of images
Home-page: https://www.github.com/night-works/keogram
Author: Joseph McCarthy
Author-email: joseph@joemccarthy.co.uk
License: MIT
Project-URL: Bug Tracker, https://www.github.com/night-works/keogram/issues
Keywords: astronomy,astrophysics,cosmology,space,science
Classifier: Programming Language :: Python :: 3
Classifier: License :: OSI Approved :: MIT License
Classifier: Operating System :: OS Independent
Requires-Python: >=3.9
License-File: LICENSE.md
Requires-Dist: Pillow (==9.4.0)
Provides-Extra: test
Requires-Dist: pytest (==7.2.1) ; extra == 'test'
Requires-Dist: coverage (==7.2.0) ; extra == 'test'
Requires-Dist: pytest-cov (==4.0.0) ; extra == 'test'
